Workbook

Sheet Instrucciones
B2: PLAN DE PRUEBAS
B3: Plataforma Web para la Gestión de Pedidos en las Cafeterías y Restaurantes de la UPB
B4: Integrantes: | C4: Ismael López Cardozo, Andrés Felipe Martínez Taborda, Valeria Gómez Arcila, Julián Eduardo Miranda Salazar
B5: Curso: | C5: Proyecto Aplicado en TIC 1
B6: Docente: | C6: Yuri Marcela Escobar
B7: Metodología: | C7: Scrumban (Sprints de 2 semanas + GitHub Projects)
B8: Base de trazabilidad: | C8: Formato_Historias_Usuarionuevo.xlsx (criterios de aceptación oficiales, HU001–HU019) y Historias_de_Usuario_UPB_Food_actualizado_v4.docx (funcionalidades agregadas y HU020–HU031)
B10: LEYENDA DE COLORES
C11: OK — Prueba superada / criterio cumplido
C12: ERROR — Prueba fallida / criterio no cumplido
C13: PENDIENTE — Aún no se ha ejecutado la prueba (celda a completar)

Sheet Plan de Pruebas Funcionales
A1: PLAN DE PRUEBAS FUNCIONALES — Trazabilidad Criterio de Aceptación → Prueba
A2: N° | B2: HU | C2: Nombre HU | D2: Sprint | E2: N° Criterio | F2: Criterio de aceptación | G2: Descripción de la prueba | H2: Datos de entrada | I2: Resultado esperado | J2: Responsable | K2: Resultado obtenido | L2: Estado (OK/ERROR/PENDIENTE)
A3: 1 | B3: HU001 | C3: Lista de restaurantes y cafeterías | D3: Sprint 1 | E3: 1 | F3: Debe mostrar un listado de restaurantes y cafeterías disponibles. | G3: Verificar el cumplimiento del criterio de aceptación: Debe mostrar un listado de restaurantes y cafeterías disponibles. | H3: Acceso y ejecución de la funcionalidad correspondiente | I3: Debe mostrar un listado de restaurantes y cafeterías disponibles. | J3: Julián Miranda | K3: Cumple según lo verificado en la prueba de seguridad ejecutada | L3: OK
A4: 2 | B4: HU001 | C4: Lista de restaurantes y cafeterías | D4: Sprint 1 | E4: 2 | F4: La lista debe visualizarse en formato vertical tipo tarjetas. | G4: Verificar el cumplimiento del criterio de aceptación: La lista debe visualizarse en formato vertical tipo tarjetas. | H4: Formulario con campos vacíos y con formatos inválidos | I4: La lista debe visualizarse en formato vertical tipo tarjetas. | J4: Julián Miranda | K4: Cumple según lo verificado en la prueba de seguridad ejecutada | L4: OK
A5: 3 | B5: HU001 | C5: Lista de restaurantes y cafeterías | D5: Sprint 1 | E5: 3 | F5: La pantalla debe ser responsive para la página web. | G5: Verificar el cumplimiento del criterio de aceptación: La pantalla debe ser responsive para la página web. | H5: Acceso desde distintos tamaños de pantalla (móvil, tablet, escritorio) | I5: La pantalla debe ser responsive para la página web. | J5: Julián Miranda | K5: Cumple según lo verificado en la prueba de seguridad ejecutada | L5: OK
A6: 4 | B6: HU001 | C6: Lista de restaurantes y cafeterías | D6: Sprint 1 | E6: 4 | F6: El tiempo de carga no debe superar los 3 segundos. | G6: Verificar el cumplimiento del criterio de aceptación: El tiempo de carga no debe superar los 3 segundos. | H6: Medición de tiempo de respuesta (cronómetro / DevTools Network) | I6: El tiempo de carga no debe superar los 3 segundos. | J6: Julián Miranda | K6: Cumple según lo verificado en la prueba de seguridad ejecutada | L6: OK
A7: 5 | B7: HU001 | C7: Lista de restaurantes y cafeterías | D7: Sprint 1 | E7: 5 | F7: (Funcionalidad agregada) El buscador de cafeterías debe filtrar por nombre. | G7: Escribir parte del nombre de una cafetería en el campo de búsqueda de la lista. | H7: Texto parcial de un nombre existente (ej. 'caf') | I7: La lista muestra solo las cafeterías cuyo nombre coincide. | J7: Julián Miranda | K7: Pendiente de ejecutar | L7: PENDIENTE
A8: 6 | B8: HU001 | C8: Lista de restaurantes y cafeterías | D8: Sprint 1 | E8: 6 | F8: (Funcionalidad agregada) El buscador debe filtrar por ubicación y por estado. | G8: Buscar por bloque/ubicación y por estado (Abierto, Cerrado, Alta demanda). | H8: Ubicación existente y estado 'Abierto' | I8: Se listan solo las cafeterías que coinciden con la ubicación o el estado ingresado. | J8: Julián Miranda | K8: Pendiente de ejecutar | L8: PENDIENTE
A9: 7 | B9: HU001 | C9: Lista de restaurantes y cafeterías | D9: Sprint 1 | E9: 7 | F9: (Funcionalidad agregada) Debe mostrar un mensaje cuando la búsqueda no tenga resultados. | G9: Buscar un texto que no coincida con ninguna cafetería. | H9: Texto inexistente (ej. 'zzzz') | I9: Aparece un mensaje de 'sin resultados' y no se muestran tarjetas. | J9: Julián Miranda | K9: Pendiente de ejecutar | L9: PENDIENTE
A10: 8 | B10: HU002 | C10: Card Restaurante | D10: Sprint 1 | E10: 1 | F10: La card debe mostrar nombre del establecimiento. | G10: Verificar el cumplimiento del criterio de aceptación: La card debe mostrar nombre del establecimiento. | H10: Acceso y ejecución de la funcionalidad correspondiente | I10: La card debe mostrar nombre del establecimiento. | J10: Valeria Gómez | K10: Cumple según lo verificado en la prueba de seguridad ejecutada | L10: OK
A11: 9 | B11: HU002 | C11: Card Restaurante | D11: Sprint 1 | E11: 2 | F11: Debe mostrar imagen representativa del restaurante o cafetería. | G11: Verificar el cumplimiento del criterio de aceptación: Debe mostrar imagen representativa del restaurante o cafetería. | H11: Acceso y ejecución de la funcionalidad correspondiente | I11: Debe mostrar imagen representativa del restaurante o cafetería. | J11: Valeria Gómez | K11: Cumple según lo verificado en la prueba de seguridad ejecutada | L11: OK
A12: 10 | B12: HU002 | C12: Card Restaurante | D12: Sprint 1 | E12: 3 | F12: Debe mostrar ubicación o bloque asociado. | G12: Verificar el cumplimiento del criterio de aceptación: Debe mostrar ubicación o bloque asociado. | H12: Acceso y ejecución de la funcionalidad correspondiente | I12: Debe mostrar ubicación o bloque asociado. | J12: Valeria Gómez | K12: Cumple según lo verificado en la prueba de seguridad ejecutada | L12: OK
A13: 11 | B13: HU002 | C13: Card Restaurante | D13: Sprint 1 | E13: 4 | F13: Debe mostrar el estado del establecimiento (Abierto, Cerrado, Alta demanda, etc.). | G13: Verificar el cumplimiento del criterio de aceptación: Debe mostrar el estado del establecimiento (Abierto, Cerrado, Alta demanda, etc.). | H13: Acceso y ejecución de la funcionalidad correspondiente | I13: Debe mostrar el estado del establecimiento (Abierto, Cerrado, Alta demanda, etc.). | J13: Valeria Gómez | K13: Cumple según lo verificado en la prueba de seguridad ejecutada | L13: OK
A14: 12 | B14: HU002 | C14: Card Restaurante | D14: Sprint 1 | E14: 5 | F14: Debe mostrar el tiempo estimado de los pedidos en general. | G14: Verificar el cumplimiento del criterio de aceptación: Debe mostrar el tiempo estimado de los pedidos en general. | H14: Acceso y ejecución de la funcionalidad correspondiente | I14: Debe mostrar el tiempo estimado de los pedidos en general. | J14: Valeria Gómez | K14: Cumple según lo verificado en la prueba de seguridad ejecutada | L14: OK
... A277: 275 | B277: HU031 | C277: Aprobación de solicitudes de cafeterías | D277: Sprint 4 Ext. | E277: 6 | F277: Tras aprobarse, el administrador debe poder iniciar sesión. | G277: Iniciar sesión con la cuenta aprobada. | H277: Credenciales de la cuenta aprobada | I277: El ingreso es exitoso y accede a su panel. | J277: Andrés Martínez | K277: Pendiente de ejecutar (funcionalidad aún no implementada según la HU v4) | L277: PENDIENTE

Sheet Resumen
A1: RESUMEN DE AVANCE POR HISTORIA DE USUARIO
A2: HU | B2: Nombre HU | C2: Total criterios | D2: OK | E2: ERROR | F2: PENDIENTE | G2: % Completado (OK)
A3: HU001 | B3: Lista de restaurantes y cafeterías | C3: =COUNTIF('Plan de Pruebas Funcionales'!$B$3:$B$277,A3) -> 7 | D3: =COUNTIFS('Plan de Pruebas Funcionales'!$B$3:$B$277,A3,'Plan de Pruebas Funcionales'!$L$3:$L$277,"OK") -> 4 | E3: =COUNTIFS('Plan de Pruebas Funcionales'!$B$3:$B$277,A3,'Plan de Pruebas Funcionales'!$L$3:$L$277,"ERROR") -> 0 | F3: =COUNTIFS('Plan de Pruebas Funcionales'!$B$3:$B$277,A3,'Plan de Pruebas Funcionales'!$L$3:$L$277,"PENDIENTE") -> 3 | G3: =IFERROR(D3/C3,0) -> 0.57142857
A4: HU002 | B4: Card Restaurante | C4: =COUNTIF('Plan de Pruebas Funcionales'!$B$3:$B$277,A4) -> 7 | D4: =COUNTIFS('Plan de Pruebas Funcionales'!$B$3:$B$277,A4,'Plan de Pruebas Funcionales'!$L$3:$L$277,"OK") -> 7 | E4: =COUNTIFS('Plan de Pruebas Funcionales'!$B$3:$B$277,A4,'Plan de Pruebas Funcionales'!$L$3:$L$277,"ERROR") -> 0 | F4: =COUNTIFS('Plan de Pruebas Funcionales'!$B$3:$B$277,A4,'Plan de Pruebas Funcionales'!$L$3:$L$277,"PENDIENTE") -> 0 | G4: =IFERROR(D4/C4,0) -> 1
A5: HU003 | B5: Barra de navegación | C5: =COUNTIF('Plan de Pruebas Funcionales'!$B$3:$B$277,A5) -> 12 | D5: =COUNTIFS('Plan de Pruebas Funcionales'!$B$3:$B$277,A5,'Plan de Pruebas Funcionales'!$L$3:$L$277,"OK") -> 7 | E5: =COUNTIFS('Plan de Pruebas Funcionales'!$B$3:$B$277,A5,'Plan de Pruebas Funcionales'!$L$3:$L$277,"ERROR") -> 0 | F5: =COUNTIFS('Plan de Pruebas Funcionales'!$B$3:$B$277,A5,'Plan de Pruebas Funcionales'!$L$3:$L$277,"PENDIENTE") -> 5 | G5: =IFERROR(D5/C5,0) -> 0.58333333
A6: HU004 | B6: Lista de productos | C6: =COUNTIF('Plan de Pruebas Funcionales'!$B$3:$B$277,A6) -> 7 | D6: =COUNTIFS('Plan de Pruebas Funcionales'!$B$3:$B$277,A6,'Plan de Pruebas Funcionales'!$L$3:$L$277,"OK") -> 5 | E6: =COUNTIFS('Plan de Pruebas Funcionales'!$B$3:$B$277,A6,'Plan de Pruebas Funcionales'!$L$3:$L$277,"ERROR") -> 0 | F6: =COUNTIFS('Plan de Pruebas Funcionales'!$B$3:$B$277,A6,'Plan de Pruebas Funcionales'!$L$3:$L$277,"PENDIENTE") -> 2 | G6: =IFERROR(D6/C6,0) -> 0.71428571
A7: HU005 | B7: Card producto | C7: =COUNTIF('Plan de Pruebas Funcionales'!$B$3:$B$277,A7) -> 11 | D7: =COUNTIFS('Plan de Pruebas Funcionales'!$B$3:$B$277,A7,'Plan de Pruebas Funcionales'!$L$3:$L$277,"OK") -> 7 | E7: =COUNTIFS('Plan de Pruebas Funcionales'!$B$3:$B$277,A7,'Plan de Pruebas Funcionales'!$L$3:$L$277,"ERROR") -> 0 | F7: =COUNTIFS('Plan de Pruebas Funcionales'!$B$3:$B$277,A7,'Plan de Pruebas Funcionales'!$L$3:$L$277,"PENDIENTE") -> 4 | G7: =IFERROR(D7/C7,0) -> 0.63636364
A8: HU006 | B8: Botón carrito | C8: =COUNTIF('Plan de Pruebas Funcionales'!$B$3:$B$277,A8) -> 6 | D8: =COUNTIFS('Plan de Pruebas Funcionales'!$B$3:$B$277,A8,'Plan de Pruebas Funcionales'!$L$3:$L$277,"OK") -> 4 | E8: =COUNTIFS('Plan de Pruebas Funcionales'!$B$3:$B$277,A8,'Plan de Pruebas Funcionales'!$L$3:$L$277,"ERROR") -> 0 | F8: =COUNTIFS('Plan de Pruebas Funcionales'!$B$3:$B$277,A8,'Plan de Pruebas Funcionales'!$L$3:$L$277,"PENDIENTE") -> 2 | G8: =IFERROR(D8/C8,0) -> 0.66666667
A9: HU007 | B9: Lista de pedidos | C9: =COUNTIF('Plan de Pruebas Funcionales'!$B$3:$B$277,A9) -> 5 | D9: =COUNTIFS('Plan de Pruebas Funcionales'!$B$3:$B$277,A9,'Plan de Pruebas Funcionales'!$L$3:$L$277,"OK") -> 2 | E9: =COUNTIFS('Plan de Pruebas Funcionales'!$B$3:$B$277,A9,'Plan de Pruebas Funcionales'!$L$3:$L$277,"ERROR") -> 0 | F9: =COUNTIFS('Plan de Pruebas Funcionales'!$B$3:$B$277,A9,'Plan de Pruebas Funcionales'!$L$3:$L$277,"PENDIENTE") -> 3 | G9: =IFERROR(D9/C9,0) -> 0.4
A10: HU008 | B10: Card productos pedidos | C10: =COUNTIF('Plan de Pruebas Funcionales'!$B$3:$B$277,A10) -> 11 | D10: =COUNTIFS('Plan de Pruebas Funcionales'!$B$3:$B$277,A10,'Plan de Pruebas Funcionales'!$L$3:$L$277,"OK") -> 8 | E10: =COUNTIFS('Plan de Pruebas Funcionales'!$B$3:$B$277,A10,'Plan de Pruebas Funcionales'!$L$3:$L$277,"ERROR") -> 0 | F10: =COUNTIFS('Plan de Pruebas Funcionales'!$B$3:$B$277,A10,'Plan de Pruebas Funcionales'!$L$3:$L$277,"PENDIENTE") -> 3 | G10: =IFERROR(D10/C10,0) -> 0.72727273
A11: HU009 | B11: Botón confirmar pedido | C11: =COUNTIF('Plan de Pruebas Funcionales'!$B$3:$B$277,A11) -> 8 | D11: =COUNTIFS('Plan de Pruebas Funcionales'!$B$3:$B$277,A11,'Plan de Pruebas Funcionales'!$L$3:$L$277,"OK") -> 5 | E11: =COUNTIFS('Plan de Pruebas Funcionales'!$B$3:$B$277,A11,'Plan de Pruebas Funcionales'!$L$3:$L$277,"ERROR") -> 0 | F11: =COUNTIFS('Plan de Pruebas Funcionales'!$B$3:$B$277,A11,'Plan de Pruebas Funcionales'!$L$3:$L$277,"PENDIENTE") -> 3 | G11: =IFERROR(D11/C11,0) -> 0.625
A12: HU010 | B12: Formulario identificación | C12: =COUNTIF('Plan de Pruebas Funcionales'!$B$3:$B$277,A12) -> 11 | D12: =COUNTIFS('Plan de Pruebas Funcionales'!$B$3:$B$277,A12,'Plan de Pruebas Funcionales'!$L$3:$L$277,"OK") -> 6 | E12: =COUNTIFS('Plan de Pruebas Funcionales'!$B$3:$B$277,A12,'Plan de Pruebas Funcionales'!$L$3:$L$277,"ERROR") -> 0 | F12: =COUNTIFS('Plan de Pruebas Funcionales'!$B$3:$B$277,A12,'Plan de Pruebas Funcionales'!$L$3:$L$277,"PENDIENTE") -> 5 | G12: =IFERROR(D12/C12,0) -> 0.54545455
A13: HU011 | B13: Botón continuar pago | C13: =COUNTIF('Plan de Pruebas Funcionales'!$B$3:$B$277,A13) -> 7 | D13: =COUNTIFS('Plan de Pruebas Funcionales'!$B$3:$B$277,A13,'Plan de Pruebas Funcionales'!$L$3:$L$277,"OK") -> 1 | E13: =COUNTIFS('Plan de Pruebas Funcionales'!$B$3:$B$277,A13,'Plan de Pruebas Funcionales'!$L$3:$L$277,"ERROR") -> 0 | F13: =COUNTIFS('Plan de Pruebas Funcionales'!$B$3:$B$277,A13,'Plan de Pruebas Funcionales'!$L$3:$L$277,"PENDIENTE") -> 6 | G13: =IFERROR(D13/C13,0) -> 0.14285714
A14: HU012 | B14: Formulario login | C14: =COUNTIF('Plan de Pruebas Funcionales'!$B$3:$B$277,A14) -> 10 | D14: =COUNTIFS('Plan de Pruebas Funcionales'!$B$3:$B$277,A14,'Plan de Pruebas Funcionales'!$L$3:$L$277,"OK") -> 10 | E14: =COUNTIFS('Plan de Pruebas Funcionales'!$B$3:$B$277,A14,'Plan de Pruebas Funcionales'!$L$3:$L$277,"ERROR") -> 0 | F14: =COUNTIFS('Plan de Pruebas Funcionales'!$B$3:$B$277,A14,'Plan de Pruebas Funcionales'!$L$3:$L$277,"PENDIENTE") -> 0 | G14: =IFERROR(D14/C14,0) -> 1
... A33: HU031 | B33: Aprobación de solicitudes de cafeterías | C33: =COUNTIF('Plan de Pruebas Funcionales'!$B$3:$B$277,A33) -> 6 | D33: =COUNTIFS('Plan de Pruebas Funcionales'!$B$3:$B$277,A33,'Plan de Pruebas Funcionales'!$L$3:$L$277,"OK") -> 0 | E33: =COUNTIFS('Plan de Pruebas Funcionales'!$B$3:$B$277,A33,'Plan de Pruebas Funcionales'!$L$3:$L$277,"ERROR") -> 0 | F33: =COUNTIFS('Plan de Pruebas Funcionales'!$B$3:$B$277,A33,'Plan de Pruebas Funcionales'!$L$3:$L$277,"PENDIENTE") -> 6 | G33: =IFERROR(D33/C33,0) -> 0
A34: TOTAL | C34: =SUM(C3:C33) -> 275 | D34: =SUM(D3:D33) -> 77 | E34: =SUM(E3:E33) -> 0 | F34: =SUM(F3:F33) -> 198 | G34: =IFERROR(D34/C34,0) -> 0.28

Sheet Checklist Seguridad
A1: CHECKLIST DE SEGURIDAD — Plataforma de Pedidos Cafeterías UPB
A2: Categoría | B2: Criterio | C2: ✓ / X | D2: Observaciones
A3: Autenticación | B3: Requiere usuario y contraseña | C3: ✓ | D3: Verificado en pantalla de login administrativo (HU012) y endpoints protegidos con credenciales obligatorias.
A4: Autenticación | B4: No permite acceso sin login | C4: ✓ | D4: Filtro JwtAuthenticationFilter bloquea peticiones no autenticadas retornando HTTP 401 Unauthorized.
A5: Autenticación | B5: Mantiene la sesión de forma segura mediante token (JWT) | C5: ✓ | D5: Probado y verificado en HU012 y HU023 con expiración, firma HMAC y Claims de usuario.
A6: Roles | B6: Existen roles definidos | C6: ✓ | D6: Estructurado en tabla tipo_administrador y validado por rol (Dueño, Cocina, Cliente, Universidad) según HU024.
A7: Roles | B7: Permisos diferenciados por rol | C7: ✓ | D7: AdminAuthorizationService valida que el usuario autenticado pertenezca a la cafetería y tenga el rol requerido (HU024, HU025, HU026).
A8: Datos | B8: No muestra datos sensibles en pantalla ni en respuestas de la API | C8: ✓ | D8: DTOs de respuesta excluyen explícitamente password_hash y datos sensibles (HU012, HU021, HU024).
A9: Datos | B9: No muestra contraseñas en texto plano en ninguna vista | C9: ✓ | D9: Campos tipo password con toggle de visibilidad en frontend y nunca devueltos por la API.
A10: Datos | B10: Las contraseñas se almacenan hasheadas en la base de datos | C10: ✓ | D10: Cifradas con algoritmo BCrypt (costo 10) en PostgreSQL, nunca almacenadas en texto plano.
A11: Validación | B11: Campos obligatorios validados en formularios | C11: ✓ | D11: Validaciones de campos requeridos implementadas en React y verificadas en backend con Bean Validation.
A12: Validación | B12: Evita el ingreso de datos incorrectos o mal formateados | C12: ✓ | D12: Expresiones regulares y validadores de formato para correo, teléfono celular y montos numéricos.
A13: Errores | B13: Los mensajes de error no muestran información técnica sensible | C13: ✓ | D13: Manejo centralizado de excepciones con GlobalExceptionHandler; respuestas 400, 403 y 409 sin stacktrace.
... A33: Sistema | B33: Las pruebas automáticas de autorización pasan (AdminAuthorizationServiceTest, ProductControllerTest) | C33: ✓ | D33: Suites de pruebas JUnit y MockMvc verificadas con ejecución exitosa en entorno de integración.

Sheet Checklis Ux
A1: Categoría | B1: Criterio | C1: Estado (✓ / X / PENDIENTE) | D1: Observaciones basadas en el Plan
A2: Claridad | B2: La interfaz y distribución del menú son fáciles de entender. | C2: COMPLETADO | D2: Se evaluará en la lista de restaurantes y catálogo de productos (HU001, HU004).
A3: Claridad | B3: Los textos e información son claros (precios, descripciones de productos, categorías). | C3: COMPLETADO | D3: Aplica a las cards de productos, panel de edición y seguimiento de pedido (HU005, HU018, HU020).
A4: Navegación | B4: Es fácil moverse entre pantallas y saber en qué sección está el usuario. | C4: COMPLETADO | D4: Evaluado a través de la barra de navegación fija e indicadores visuales (HU003).
A5: Navegación | B5: Transición fluida hacia el flujo de compra y pedidos (Carrito → Identificación → Pago). | C5: COMPLETADO | D5: Corresponde a los botones de acción del flujo del cliente y al pedido en tres pasos (HU006, HU007, HU009, HU011, HU022).
A6: Usabilidad | B6: Acciones principales fáciles de realizar (agregar al carrito, ajustar cantidades, confirmar). | C6: COMPLETADO | D6: Abarca los controles de cantidad y adición de ítems, y quitar/añadir ingredientes (HU005, HU006, HU008).
A7: Usabilidad | B7: El sistema responde rápido (tiempos de carga menores a 2-3 segundos). | C7: COMPLETADO | D7: Verificación transversal de rendimiento según criterios de aceptación (HU001, HU009, HU011, HU013, HU020, HU022).
A8: Formularios | B8: Campos bien etiquetados en formularios de identificación, login y edición de productos. | C8: COMPLETADO | D8: Aplica a los módulos de autenticación y captura de datos (HU010, HU012, HU018, HU019, HU021, HU025, HU029, HU030).
A9: Formularios | B9: Mensajes de validación claros en campos obligatorios o vacíos. | C9: COMPLETADO | D9: Verificación de retroalimentación inmediata ante entradas incorrectas (HU010, HU011, HU021, HU025, HU030).
A10: Diseño | B10: Diseño limpio, ordenado y estructurado mediante tarjetas/cards para ítems y pedidos. | C10: COMPLETADO | D10: Abarca la disposición visual de elementos (HU002, HU014, HU015, HU017, HU027, HU031).
A11: Diseño | B11: Uso consistente de colores en estados (ej. Abierto/Cerrado, Disponible/Agotado, Botones de acción). | C11: COMPLETADO | D11: Evaluado en el panel de administración, estado de cocina y seguimiento (HU014, HU016, HU020, HU029).
A12: Experiencia | B12: Adaptabilidad y diseño responsive en la página web (móvil, tablet, escritorio). | C12: COMPLETADO | D12: Requisito de maquetación verificado en múltiples historias (HU001, HU003, HU010, HU012, HU020, HU030).
... A24: Experiencia | B24: Los mensajes de error de carrito de una sola cafetería y de cafetería cerrada se entienden. | C24: COMPLETADO | D24: Aplica a las restricciones del carrito y del pedido (HU006, HU009).

Sheet Matriz Perfiles
A1: Matriz de Roles y Perfiles de la Aplicación (UPB Food)
A3: Rol / Perfil de Usuario | B3: Tipo de Usuario | C3: Descripción / Propósito | D3: Permisos y Funcionalidades en la App | E3: Historias de Usuario (HU) Asociadas
A4: Estudiante / Cliente | B4: Usuario Final (Público / Autenticado) | C4: Comunidad universitaria (estudiantes, docentes, administrativos) que consulta el menú y realiza pedidos anticipados para evitar filas. | D4: • Explorar lista de restaurantes y cafeterías. | E4: • HU001, HU002, HU003
D6: • Consultar menú y detalles de productos. | E6: • HU004, HU005, HU006
D8: • Gestionar el carrito de compras (agregar/quitar ítems, poner observaciones). | E8: • HU007, HU008, HU009
D10: • Identificarse con cualquier correo valido (@gmail, @hotmail, @upb.edu.co, etc). | E10: • HU010, HU011
D12: • Confirmar pedido y seleccionar método de pago. | E12: • HU022
D14: • Seguir el estado de su pedido con el código de seguimiento. | E14: • HU020
D16: • Consultar su pedido con el número de pedido y correo o teléfono. | E16: • HU021
D18: • Visualizar el historial de sus pedidos anteriores. | E18: • HU027
A19: Personal de Cocina / Operativo | B19: Usuario Interno (Restaurante) | C19: Equipo de trabajo dentro de las cafeterías encargado de preparar los pedidos y gestionar el flujo de entrega. | D19: • Acceder al panel operativo de cocina en tiempo real. | E19: • HU003, HU014, HU015
D21: • Visualizar la lista de pedidos pendientes y sus detalles (ítems, observaciones del cliente, hora). | E21: • HU014, HU015
D23: • Cambiar el estado operativo de la orden (ej. Pendiente, En preparación, Listo para recoger). | E23: • HU015
D25: • Mantener la sesión activa al recargar la página y cerrar sesión de forma segura. | E25: • HU023
D27: • Operar solo en la cafetería a la que está asignado, con permisos del rol de cocina. | E27: • HU024
A28: Administrador de Cafetería | B28: Usuario Administrativo | C28: Encargado del establecimiento que gestiona el catálogo de productos, la disponibilidad y la operación del local. | D28: • Iniciar sesión segura con credenciales administrativas. | E28: • HU012, HU013
D30: • Mantener la sesión activa al recargar la página y cerrar sesión de forma segura. | E30: • HU023
D32: • Consultar y filtrar el inventario/catálogo de productos. | E32: • HU016, HU017
D34: • Seleccionar la cafetería a administrar cuando tiene más de una asignación. | E34: • HU016
D36: • Habilitar o inhabilitar productos en tiempo real (Disponible / Agotado). | E36: • HU018, HU019
D38: • Editar información de productos (precios, descripciones, ingredientes extra). | E38: • HU018
D40: • Gestionar las adiciones de los productos. | E40: • HU018
D42: • Crear nuevos productos en el catálogo y cargar su imagen. | E42: • HU019
D44: • Retirar productos del menú. | E44: • HU017
D46: • Modificar únicamente los productos de su propia cafetería. | E46: • HU026
D48: • Registrar administradores de cocina y retirarles el acceso. | E48: • HU025
D50: • Ver métricas reales de pedidos y ventas en el panel administrativo. | E50: • HU028
D52: • Cambiar el estado de la cafetería (Abierto, Cerrado, Alta demanda), el tiempo estimado y sus datos. | E52: • HU029
... D56: • Registrarse junto con su cafetería; la solicitud queda pendiente de aprobación. | E56: • HU030
A57: Persona encargada de la universidad | B57: Usuario Interno (Universidad) | C57: Responsable de la universidad que controla qué cafeterías entran a la plataforma, aprobando o rechazando las solicitudes de registro. | D57: • Revisar las solicitudes de registro pendientes (datos de la cafetería y del administrador). | E57: • HU031
D59: • Aceptar o rechazar solicitudes; al aceptar se activa la cuenta y la cafetería aparece en la lista. | E59: • HU031
D61: • Ingresar con un rol propio de aprobación, que se suma a los roles de acceso. | E61: • HU024, HU031

Sheet Matriz de Roles y Perfiles
A1: Matriz de Roles y Perfiles
A3: Nombre / Perfil | B3: Rol en el Equipo | C3: Enfoque de Pruebas asignadas | D3: Historias de Usuario (HU) a cargo según Checklist
A4: Ismael López | B4: Data Scientist & QA Manager | C4: Validaciones funcionales clave, paneles operativos (cocina y admin) y flujos de ingreso. Pruebas de control de acceso por rol y cafetería, aislamiento de productos, gestión de administradores de cocina y consulta de pedidos. Lidera el aseguramiento de calidad general. | D4: • HU005: Card producto
D6: • HU013: Botón ingreso
D8: • HU014: Lista de pedidos (cocina)
D10: • HU016: Lista de productos (admin)
D12: • HU019: Botón añadir producto
D14: • HU021: Consulta de pedido por número y correo o teléfono
D16: • HU024: Control de acceso por rol y cafetería
D18: • HU025: Gestión de administradores de cocina
D20: • HU026: Aislamiento de productos por cafetería
A21: Valeria Gómez | B21: Scrum Master & UI/UX Designer | C21: Pruebas centradas en la experiencia de usuario (UX), componentes visuales, estados de botones y validación del carrito de compras. Incluye seguimiento y historial de pedidos del cliente, métricas del panel administrativo y estado de la cafetería. | D21: • HU002: Card Restaurante
D23: • HU006: Botón carrito
D25: • HU007: Lista de pedidos
D27: • HU015: Card de pedidos (cocina)
D29: • HU017: Card de productos (admin)
D31: • HU020: Seguimiento de pedido por código
D33: • HU027: Historial de pedidos del cliente
D35: • HU028: Métricas reales del panel administrativo
D37: • HU029: Cambio de estado de la cafetería
A38: Julián Miranda | B38: Frontend Engineer | C38: Pruebas de componentes de navegación (barra dinámica y rutas por tipo de usuario), renderizado de listas desde el API, buscadores, selector de cafetería y formularios de captura de datos del cliente (incluida la hora de recogida). | D38: • HU001: Lista de restaurantes y cafeterías
D40: • HU003: Barra de navegación
D42: • HU004: Lista de productos
D44: • HU010: Formulario identificación
A45: Andrés Martínez | B45: Product Owner & Tech Lead | C45: Pruebas de la lógica de negocio profunda, seguridad (login backend, sesión persistente y refresh token), transiciones de estado y confirmaciones de pago (portal de pago simulado). Incluye registro y aprobación de solicitudes de cafeterías. | D45: • HU008: Card de productos pedidos
D47: • HU009: Botón confirmar pedido
D49: • HU011: Botón continuar pago
D51: • HU012: Formulario de login
D53: • HU022: Portal de pago simulado
D55: • HU023: Sesión persistente y cierre de sesión del administrador
D57: • HU030: Registro de administrador y cafetería
D59: • HU031: Aprobación de solicitudes de registro de cafeterías
A60: Andrés M. & Julián M. | B60: Tech Lead + Frontend Eng. | C60: Pruebas de integración conjunta (Backend + Frontend) donde la edición de la base de datos impacta directamente la interfaz, incluidas las adiciones de productos. | D60: • HU018: Panel de edición de producto
